alignak_checks_mongodb/__init__.py
alignak_checks_mongodb-1.1.3.data/data/share/alignak/etc/arbiter/packs/mongodb/commands.cfg
alignak_checks_mongodb-1.1.3.data/data/share/alignak/etc/arbiter/packs/mongodb/groups.cfg
alignak_checks_mongodb-1.1.3.data/data/share/alignak/etc/arbiter/packs/mongodb/templates.cfg
alignak_checks_mongodb-1.1.3.data/data/share/alignak/etc/backend-json/mongodb/commands.json
alignak_checks_mongodb-1.1.3.data/data/share/alignak/etc/backend-json/mongodb/hostgroups.json
alignak_checks_mongodb-1.1.3.data/data/share/alignak/etc/backend-json/mongodb/hosts-templates.json
alignak_checks_mongodb-1.1.3.data/data/share/alignak/etc/backend-json/mongodb/servicegroups.json
alignak_checks_mongodb-1.1.3.data/data/share/alignak/etc/backend-json/mongodb/services-templates.json
alignak_checks_mongodb-1.1.3.data/data/share/alignak/etc/backend-json/mongodb/setup.sh
alignak_checks_mongodb-1.1.3.data/data/share/alignak/libexec/LICENSE
alignak_checks_mongodb-1.1.3.data/data/share/alignak/libexec/README.md
alignak_checks_mongodb-1.1.3.data/data/share/alignak/libexec/check_mongodb.py
alignak_checks_mongodb-1.1.3.data/data/share/alignak/libexec/requirements
alignak_checks_mongodb-1.1.3.dist-info/LICENSE
alignak_checks_mongodb-1.1.3.dist-info/METADATA
alignak_checks_mongodb-1.1.3.dist-info/WHEEL
alignak_checks_mongodb-1.1.3.dist-info/top_level.txt
alignak_checks_mongodb-1.1.3.dist-info/RECORD
